euclidlib/__init__.py
euclidlib/_util.py
euclidlib/_version.py
euclidlib/phz.py
euclidlib/le3/__init__.py
euclidlib/le3/pk_gc.py
euclidlib/le3/pk_wl.py
euclidlib/le3/twopcf_wl.py
euclidlib-2026.1.dist-info/METADATA
euclidlib-2026.1.dist-info/WHEEL
euclidlib-2026.1.dist-info/licenses/LICENSE
euclidlib-2026.1.dist-info/RECORD
